instapv/__init__.py
instapv/config.py
instapv/exceptions.py
instapv/instagram.py
instapv/logger.py
instapv/ig/__init__.py
instapv/ig/account.py
instapv/ig/business.py
instapv/ig/collection.py
instapv/ig/live.py
instapv/ig/media.py
instapv/ig/user.py
instapv/response/__init__.py
instapv/response/collection_feed.py
instapv/response/comments.py
instapv/response/create_collection.py
instapv/response/edit_collection.py
instapv/response/followers.py
instapv/response/following.py
instapv/response/friendship.py
instapv/response/generic.py
instapv/response/live_info.py
instapv/response/login.py
instapv/response/media_info.py
instapv/response/media_items_info.py
instapv/response/self_user_feed.py
instapv/response/send_comment.py
instapv/response/two_factor_info.py
instapv/response/user_info_by_name.py
instapv/response/user_response.py
instapv/utils/ImageUtils.py
instapv/utils/__init__.py
instapv/utils/auto_mapper.py
instapv/utils/tools.py
instapv/utils/devices/__init__.py
instapv/utils/devices/device.py
instapvapi-0.1.6.dist-info/METADATA
instapvapi-0.1.6.dist-info/WHEEL
instapvapi-0.1.6.dist-info/top_level.txt
instapvapi-0.1.6.dist-info/RECORD
