Metadata-Version: 2.1
Name: instapvapi
Version: 0.1.6
Summary: An unofficial instagram private api.
Home-page: https://github.com/its0x4d/instagramapi-python
Author: UWSGI
Author-email: mosydev2016@gmail.com
License: MIT
Platform: any
Classifier: Programming Language :: Python :: 3
Classifier: License :: OSI Approved :: MIT License
Classifier: Operating System :: OS Independent
Requires-Dist: packaging
Requires-Dist: colorama
Requires-Dist: requests
